ds4se/None.py
ds4se/__init__.py
ds4se/_nbdev.py
ds4se/facade.py
ds4se/sentence_transformers.py
ds4se/vis.py
ds4se/benchmark/__init__.py
ds4se/benchmark/codegen.py
ds4se/benchmark/i.py
ds4se/benchmark/traceability.py
ds4se/data/__init__.py
ds4se/data/exploratory.py
ds4se/data/management.py
ds4se/data/preprocessing.py
ds4se/data/representation.py
ds4se/data/exploratory/__init__.py
ds4se/data/exploratory/information.py
ds4se/data/exploratory/stats.py
ds4se/data/exploratory/visualize.py
ds4se/desc/__init__.py
ds4se/desc/stats.py
ds4se/desc/metrics/__init__.py
ds4se/desc/metrics/java.py
ds4se/desc/metrics/main.py
ds4se/desc/metrics/se.py
ds4se/exp/__init__.py
ds4se/exp/i.py
ds4se/exp/info-[inspect].py
ds4se/exp/info.py
ds4se/exp/csnc/__init__.py
ds4se/exp/csnc/java.py
ds4se/exp/csnc/python.py
ds4se/exp/gen/__init__.py
ds4se/exp/gen/code.py
ds4se/exp/traceability/__init__.py
ds4se/exp/traceability/java.py
ds4se/inf/__init__.py
ds4se/inf/bayesian.py
ds4se/inf/causal.py
ds4se/inf/i.py
ds4se/mgmnt/__init__.py
ds4se/mgmnt/corpus.py
ds4se/mgmnt/db/__init__.py
ds4se/mgmnt/db/mongo.py
ds4se/mgmnt/prep/__init__.py
ds4se/mgmnt/prep/bpe.py
ds4se/mgmnt/prep/conv.py
ds4se/mgmnt/prep/i.py
ds4se/mgmnt/prep/nltk.py
ds4se/mgmnt/prep/traceability.py
ds4se/mining/__init__.py
ds4se/mining/unsupervised/__init__.py
ds4se/mining/unsupervised/eval.py
ds4se/mining/unsupervised/traceability/__init__.py
ds4se/mining/unsupervised/traceability/approach.py
ds4se/mining/unsupervised/traceability/approach[cisco].py
ds4se/mining/unsupervised/traceability/eda.py
ds4se/mining/unsupervised/traceability/eval.py
ds4se/mining/unsupervised/traceability/ida.py
ds4se/mining/unsupervised/traceability/approach/__init__.py
ds4se/mining/unsupervised/traceability/approach/cisco.py
ds4se/mining/unsupervised/traceability/approach/libest.py
ds4se/model/DS4SE.png
ds4se/model/__init__.py
ds4se/model/doc2vec_libest.model
ds4se/model/test.model
ds4se/model/test.vocab
ds4se/model/train.py
ds4se/model/val.csv
ds4se-0.2.1.dist-info/LICENSE
ds4se-0.2.1.dist-info/METADATA
ds4se-0.2.1.dist-info/WHEEL
ds4se-0.2.1.dist-info/entry_points.txt
ds4se-0.2.1.dist-info/top_level.txt
ds4se-0.2.1.dist-info/RECORD
