Metadata-Version: 2.1
Name: ds4se
Version: 0.2.1
Summary: Data Science for Software Engieering (ds4se) is an academic initiative to perform exploratory analysis on software engieering artifact and metadata. Data Management, Analysis, and Benchmarking for DL and Traceability
Home-page: https://github.com/ncoop57/ds4se
Author: Semeru Lab
Author-email: semeru.lab.wm@gmail.com
License: Apache Software License 2.0
Keywords: data science software engineering management analysis benchmarking
Platform: UNKNOWN
Classifier: Development Status :: 3 - Alpha
Classifier: Intended Audience :: Science/Research
Classifier: License :: OSI Approved :: Apache Software License
Classifier: Natural Language :: English
Classifier: Programming Language :: Python :: 3.6
Classifier: Programming Language :: Python :: 3.7
Classifier: Programming Language :: Python :: 3.8
Requires-Python: >=3.6
